<?xml version="1.0" encoding="UTF-8"?>
<beans xmlns="http://www.springframework.org/schema/beans"
       xmlns:xsi="http://www.w3.org/2001/XMLSchema-instance"
       xmlns:mvc="http://www.springframework.org/schema/mvc"
       xmlns:context="http://www.springframework.org/schema/context"
       xsi:schemaLocation="http://www.springframework.org/schema/beans
       http://www.springframework.org/schema/beans/spring-beans.xsd
       http://www.springframework.org/schema/mvc
       http://www.springframework.org/schema/mvc/spring-mvc-4.0.xsd
       http://www.springframework.org/schema/context
       http://www.springframework.org/schema/context/spring-context-4.0.xsd">

    <!--imports configurations from other modules -->
    <import resource="classpath*:service-config.xml"/>
    <import resource="classpath*:dao-config.xml"/>

    <mvc:annotation-driven validator="validator"/>
    <context:component-scan base-package="by.kanarski.booking.controllers"/>

    <!-- show path to UI resources files-->
    <mvc:resources mapping="/assets/**" location="/assets/"/>

    <!--<bean id="viewResolver"-->
          <!--class="org.springframework.web.servlet.view.InternalResourceViewResolver">-->
        <!--<property name="prefix" value="/WEB-INF/jsp/"/>-->
        <!--<property name="suffix" value=".jsp"/>-->
    <!--</bean>-->

    <bean id="tilesConfigurer" class="org.springframework.web.servlet.view.tiles3.TilesConfigurer">
        <property name="definitions" value="/WEB-INF/tiles.xml"/>
    </bean>

    <bean id="tilesViewResolver" class="org.springframework.web.servlet.view.UrlBasedViewResolver">
        <property name="viewClass" value="org.springframework.web.servlet.view.tiles3.TilesView"/>
    </bean>

    <bean id="localeResolver"
          class="org.springframework.web.servlet.i18n.SessionLocaleResolver">
        <property name="defaultLocale" value="ru"/>
    </bean>

    <!-- show path to resource bundle messages-->
    <bean id="messageSource" class="org.springframework.context.support.ReloadableResourceBundleMessageSource">
        <property name="basename" value="classpath:I18N/message"/>
        <property name="defaultEncoding" value="UTF-8"/>
    </bean>

    <bean id="validationMessageSource" class="org.springframework.context.support.ReloadableResourceBundleMessageSource">
        <property name="basename" value="classpath:I18N/validationMessage" />
        <property name="defaultEncoding" value="UTF-8"/>
    </bean>

    <bean name="validator"  class="org.springframework.validation.beanvalidation.LocalValidatorFactoryBean">
        <property name="validationMessageSource" ref="validationMessageSource"/>
    </bean>

    <mvc:interceptors>
        <bean class="org.springframework.web.servlet.i18n.LocaleChangeInterceptor">
            <property name="paramName" value="locale"/>
        </bean>
    </mvc:interceptors>
</beans>